{
  "features": [
    {
      "type": "Feature",
      "properties": {
        "place_name": "6 Avenue de Provence, Paris, 75009, France",
        "title": "cic",
        "description": "siège social"
      },
      "geometry": {
        "coordinates": [
          2.334406,
          48.874692
        ],
        "type": "Point"
      },
      "id": "address.8602094865131520"
    }
  ],
  "type": "FeatureCollection"
}