{
  "features": [
    {
      "type": "Feature",
      "properties": {
        "place_name": "185 Berry St, San Francisco, California 94107, United States",
        "title": "stripe",
        "description": "siège social"
      },
      "geometry": {
        "coordinates": [
          -122.391831,
          37.77657
        ],
        "type": "Point"
      },
      "id": "address.1333644511051530"
    }
  ],
  "type": "FeatureCollection"
}