{
  "features": [
    {
      "type": "Feature",
      "properties": {
        "place_name": "Schubertring 11, Innere Stadt, Wien 1010, Austria",
        "title": "western union",
        "description": "siège social"
      },
      "geometry": {
        "coordinates": [
          16.375498,
          48.201842
        ],
        "type": "Point"
      },
      "id": "address.1763179729"
    }
  ],
  "type": "FeatureCollection"
}