{
  "features": [
    {
      "type": "Feature",
      "properties": {
        "place_name": "62 Buckingham Gate, City of Westminster, London, Greater London, England SW1H 0PY, United Kingdom",
        "title": "worldremit",
        "description": "siège social"
      },
      "geometry": {
        "coordinates": [
          -0.136051,
          51.49816
        ],
        "type": "Point"
      },
      "id": "address.9962977091501440"
    }
  ],
  "type": "FeatureCollection"
}