{
  "features": [
    {
      "type": "Feature",
      "properties": {
        "place_name": "10 Corporate Dr, Burlington, Massachusetts 01803, United States",
        "title": "VPSlink",
        "description": "10 Corporate Dr., Suite 300, Burlington, MA 01803"
      },
      "geometry": {
        "coordinates": [
          -71.192339,
          42.496835
        ],
        "type": "Point"
      },
      "id": "address.18399290791495220"
    }
  ],
  "type": "FeatureCollection"
}