{
  "features": [
    {
      "type": "Feature",
      "properties": {
        "place_name": "180 Boulevard de Verdun, Courbevoie, Hauts-de-Seine 92400, France",
        "title": "paritel",
        "description": "siège social"
      },
      "geometry": {
        "coordinates": [
          2.256021,
          48.905163
        ],
        "type": "Point"
      },
      "id": "address.10240918218545540"
    }
  ],
  "type": "FeatureCollection"
}