{
  "features": [
    {
      "type": "Feature",
      "properties": {
        "place_name": "1 Infinite Loop, Cupertino, California 95014, United States",
        "title": "Apple",
        "description": "siège social"
      },
      "geometry": {
        "coordinates": [
          -122.030212,
          37.331845
        ],
        "type": "Point"
      },
      "id": "address.6071763983100160"
    }
  ],
  "type": "FeatureCollection"
}