{
  "features": [
    {
      "type": "Feature",
      "properties": {
        "place_name": "14460, Colombelles, Calvados, France",
        "title": "Dépôt Numérique",
        "description": "siège social"
      },
      "geometry": {
        "coordinates": [
          -0.290409,
          49.200201
        ],
        "type": "Point"
      },
      "id": "postcode.8369899735464520"
    }
  ],
  "type": "FeatureCollection"
}